registrable/__init__.py
registrable/choices.py
sample/__init__.py
sample/asgi.py
sample/manage.py
sample/settings.py
sample/urls.py
sample/wsgi.py
django_registrable_choices-0.0.1a0.dist-info/LICENSE
django_registrable_choices-0.0.1a0.dist-info/METADATA
django_registrable_choices-0.0.1a0.dist-info/WHEEL
django_registrable_choices-0.0.1a0.dist-info/top_level.txt
django_registrable_choices-0.0.1a0.dist-info/RECORD
