Metadata-Version: 2.1
Name: django-registrable-choices
Version: 0.0.1a0
Summary: Django Registrable Lazy Choices
Home-page: https://github.com/hyper-coding/dj-choices
Author: Sidnei Pereira
Author-email: sidnei@hprs.com.br
License: UNKNOWN
Platform: UNKNOWN
Classifier: Programming Language :: Python :: 3
Classifier: License :: OSI Approved :: BSD License
Classifier: Operating System :: OS Independent
Requires-Python: >=3.6
